pycope/__init__.py
pycope/context.py
pycope/executable.py
pycope/layer.py
pycope/prioritizers.py
pycope/strategy.py
pycope-0.1.1.dist-info/METADATA
pycope-0.1.1.dist-info/RECORD
pycope-0.1.1.dist-info/WHEEL
pycope-0.1.1.dist-info/top_level.txt
