Metadata-Version: 2.1
Name: pycope
Version: 0.1.1
Summary: A Context-Oriented Programming Extension for Python.
Home-page: http://www.github.com/pycope
Author: Jacob Waffle
Author-email: thejakewaffle@gmail.com
License: Apache2
Platform: UNKNOWN
Requires-Dist: immutables
